yahoo_search_api/__init__.py
yahoo_search_api/api_client.py
yahoo_search_api/configuration.py
yahoo_search_api/exceptions.py
yahoo_search_api/rest.py
yahoo_search_api/api/__init__.py
yahoo_search_api/api/account_link_service_api.py
yahoo_search_api/api/account_management_service_api.py
yahoo_search_api/api/account_service_api.py
yahoo_search_api/api/account_shared_service_api.py
yahoo_search_api/api/account_tracking_url_service_api.py
yahoo_search_api/api/ad_group_ad_label_service_api.py
yahoo_search_api/api/ad_group_ad_service_api.py
yahoo_search_api/api/ad_group_bid_multiplier_service_api.py
yahoo_search_api/api/ad_group_criterion_label_service_api.py
yahoo_search_api/api/ad_group_criterion_service_api.py
yahoo_search_api/api/ad_group_feed_service_api.py
yahoo_search_api/api/ad_group_label_service_api.py
yahoo_search_api/api/ad_group_retargeting_list_service_api.py
yahoo_search_api/api/ad_group_service_api.py
yahoo_search_api/api/ad_group_webpage_service_api.py
yahoo_search_api/api/app_link_service_api.py
yahoo_search_api/api/audit_log_service_api.py
yahoo_search_api/api/balance_service_api.py
yahoo_search_api/api/bidding_strategy_service_api.py
yahoo_search_api/api/budget_order_service_api.py
yahoo_search_api/api/campaign_criterion_service_api.py
yahoo_search_api/api/campaign_export_service_api.py
yahoo_search_api/api/campaign_feed_service_api.py
yahoo_search_api/api/campaign_label_service_api.py
yahoo_search_api/api/campaign_retargeting_list_service_api.py
yahoo_search_api/api/campaign_service_api.py
yahoo_search_api/api/campaign_shared_set_service_api.py
yahoo_search_api/api/campaign_target_service_api.py
yahoo_search_api/api/campaign_webpage_service_api.py
yahoo_search_api/api/conversion_tracker_service_api.py
yahoo_search_api/api/dictionary_service_api.py
yahoo_search_api/api/feed_item_service_api.py
yahoo_search_api/api/feed_service_api.py
yahoo_search_api/api/keyword_estimator_service_api.py
yahoo_search_api/api/keyword_forecast_metrics_service_api.py
yahoo_search_api-1.0.0.dist-info/METADATA
yahoo_search_api-1.0.0.dist-info/WHEEL
yahoo_search_api-1.0.0.dist-info/top_level.txt
yahoo_search_api-1.0.0.dist-info/RECORD
